Metadata-Version: 2.4
Name: hack4u_bichos
Version: 0.1.0
Summary: Una biblioteca para constular cursos de hack4u.
Home-page: https://hack4u.io
Author:  Emmanuel Bustamante
Dynamic: author
Dynamic: description
Dynamic: description-content-type
Dynamic: home-page
Dynamic: summary
